objectrl/__init__.py
objectrl/harvest.py
objectrl/main.py
objectrl/agents/__init__.py
objectrl/agents/base_agent.py
objectrl/config/__init__.py
objectrl/config/config.py
objectrl/config/model.py
objectrl/config/utils.py
objectrl/config/model_configs/__init__.py
objectrl/config/model_configs/bnnsac.py
objectrl/config/model_configs/ddpg.py
objectrl/config/model_configs/dqn.py
objectrl/config/model_configs/drnd.py
objectrl/config/model_configs/oac.py
objectrl/config/model_configs/pbac.py
objectrl/config/model_configs/ppo.py
objectrl/config/model_configs/redq.py
objectrl/config/model_configs/sac.py
objectrl/config/model_configs/td3.py
objectrl/experiments/__init__.py
objectrl/experiments/base_experiment.py
objectrl/experiments/control_experiment.py
objectrl/loggers/__init__.py
objectrl/loggers/logger.py
objectrl/models/__init__.py
objectrl/models/bnnsac.py
objectrl/models/ddpg.py
objectrl/models/dqn.py
objectrl/models/drnd.py
objectrl/models/get_model.py
objectrl/models/oac.py
objectrl/models/pbac.py
objectrl/models/ppo.py
objectrl/models/redq.py
objectrl/models/sac.py
objectrl/models/td3.py
objectrl/models/basic/ac.py
objectrl/models/basic/actor.py
objectrl/models/basic/critic.py
objectrl/models/basic/ensemble.py
objectrl/models/basic/loss.py
objectrl/nets/__init__.py
objectrl/nets/actor_nets.py
objectrl/nets/critic_nets.py
objectrl/nets/layers/bayesian_layers.py
objectrl/nets/layers/heads.py
objectrl/replay_buffers/__init__.py
objectrl/replay_buffers/experience_memory.py
objectrl/utils/__init__.py
objectrl/utils/custom_act.py
objectrl/utils/harvest_utils.py
objectrl/utils/make_env.py
objectrl/utils/net_utils.py
objectrl/utils/utils.py
objectrl/utils/environment/dmc_wrappers.py
objectrl/utils/environment/metaworld_wrappers.py
objectrl/utils/environment/noisy_wrappers.py
objectrl/utils/environment/reward_wrappers.py
objectrl-0.2.0.dist-info/licenses/LICENSE
objectrl-0.2.0.dist-info/METADATA
objectrl-0.2.0.dist-info/WHEEL
objectrl-0.2.0.dist-info/top_level.txt
objectrl-0.2.0.dist-info/RECORD
