Metadata-Version: 2.4
Name: objectrl
Version: 0.2.0
Summary: ObjectRL: An Object-Oriented Reinforcement Learning Codebase
Author-email: Abdullah Akgul <akgul@imada.sdu.dk>, Bahareh Tasdighi <tasdighi@imada.sdu.dk>, Gulcin Baykal Can <baykalg@imada.sdu.dk>, Manuel Haussmann <haussmann@imada.sdu.dk>, Melih Kandemir <kandemir@imada.sdu.dk>, Nicklas Werge <werge@sdu.dk>, Yi-Shan Wu <yswu@imada.sdu.dk>
License: GPL-3.0-or-later
Classifier: Development Status :: 3 - Alpha
Classifier: Intended Audience :: Science/Research
Classifier: Programming Language :: Python :: 3.12
Requires-Python: >=3.12
License-File: LICENSE
Requires-Dist: gymnasium[mujoco]>=1.1.1
Requires-Dist: torch>=2.7.0
Requires-Dist: torchrl>=0.8.1
Requires-Dist: tqdm>=4.67.1
Requires-Dist: tyro>=0.9.22
Requires-Dist: matplotlib>=3.10.3
Requires-Dist: pandas>=2.2.3
Requires-Dist: tabulate>=0.9.0
Requires-Dist: pyyaml>=6.0.2
Requires-Dist: seaborn>=0.13.2
Requires-Dist: pyqt6>=6.9.1
Requires-Dist: dm-control>=1.0.31
Requires-Dist: metaworld>=3.0.0
Provides-Extra: docs
Requires-Dist: sphinx>=8.2.3; extra == "docs"
Requires-Dist: sphinx-book-theme>=1.1.4; extra == "docs"
Requires-Dist: sphinxcontrib-pseudocode>=0.7.0; extra == "docs"
Requires-Dist: sphinx-simplepdf>=1.6.0; extra == "docs"
Requires-Dist: sphinx-tabs>=3.4.7; extra == "docs"
Requires-Dist: sphinx-copybutton>=0.5.2; extra == "docs"
Provides-Extra: tests
Requires-Dist: pytest; extra == "tests"
Provides-Extra: dev
Requires-Dist: black>=25.1.0; extra == "dev"
Requires-Dist: ruff>=0.12.1; extra == "dev"
Requires-Dist: ty>=0.0.1a13; extra == "dev"
Dynamic: license-file
